django_cluster_redis/__init__.py
django_cluster_redis/cache.py
django_cluster_redis-1.0.5.dist-info/DESCRIPTION.rst
django_cluster_redis-1.0.5.dist-info/METADATA
django_cluster_redis-1.0.5.dist-info/RECORD
django_cluster_redis-1.0.5.dist-info/WHEEL
django_cluster_redis-1.0.5.dist-info/metadata.json
django_cluster_redis-1.0.5.dist-info/top_level.txt
