Metadata-Version: 2.0
Name: django-cluster-redis
Version: 1.0.5
Summary: django cluster redis
Home-page: https://github.com/deforestg/django-cluster-redis
Author: Gabriel de Forest
Author-email: UNKNOWN
License: UNKNOWN
Keywords: django cluster redis aws elasticcache
Platform: UNKNOWN
Requires-Dist: Django (>=1.8.1)
Requires-Dist: django-redis (>=4.7.0)
